freckle_client/__init__.py
freckle_client/client.py
freckle_client/exceptions.py
freckle_client/tests/__init__.py
noko_client/__init__.py
noko_client/client.py
noko_client/base_client/__init__.py
noko_client/base_client/base_client.py
noko_client/schemas/__init__.py
noko_client/schemas/entries_parameters.py
noko_client/schemas/expenses_parameters.py
noko_client/schemas/invoice_parameters.py
noko_client/schemas/project_groups_parameters.py
noko_client/schemas/projects_parameters.py
noko_client/schemas/tags_parameters.py
noko_client/schemas/teams_parameters.py
noko_client/schemas/users_parameters.py
noko_client/schemas/utilities.py
noko_client/schemas/validators.py
python_freckle_client-1.1.2.dist-info/AUTHORS
python_freckle_client-1.1.2.dist-info/LICENSE
python_freckle_client-1.1.2.dist-info/METADATA
python_freckle_client-1.1.2.dist-info/WHEEL
python_freckle_client-1.1.2.dist-info/top_level.txt
python_freckle_client-1.1.2.dist-info/RECORD
