Metadata-Version: 2.1
Name: python-freckle-client
Version: 1.1.2
Summary: A super simple Freckle/Noko API client implementation.
Home-page: https://github.com/ombulabs/python-freckle-client
Author: OmbuLabs - The Lean Software Boutique, LLC
Author-email: hello@ombulabs.com
License: The MIT License
Keywords: nokotime,noko,api,client,freckle
Platform: OS Independent
License-File: LICENSE
License-File: AUTHORS
Requires-Dist: requests
Requires-Dist: pydantic
Requires-Dist: python-dateutil
Provides-Extra: dev
Requires-Dist: black ; extra == 'dev'
Requires-Dist: flake8 ; extra == 'dev'
Requires-Dist: isort ; extra == 'dev'
Requires-Dist: mypy ; extra == 'dev'
Requires-Dist: pylint ; extra == 'dev'
